{"is_source_file": true, "format": "JavaScript", "description": "A client module for interacting with the Recipe Hub backend API, providing functions for authenticated GET, POST, PATCH, and DELETE requests, managing bearer tokens, and constructing request headers.", "external_files": ["fetch"], "external_methods": ["localStorage.getItem", "localStorage.setItem", "localStorage.removeItem"], "published": ["setAuthToken", "apiGet", "apiPost", "apiPatch", "apiDelete"], "classes": [], "methods": [{"name": "setAuthToken(token)", "description": "Stores or removes the bearer token in localStorage to facilitate authenticated requests.", "scope": "", "scopeKind": ""}, {"name": "apiGet(path, auth = false, params)", "description": "Performs an HTTP GET request to the specified API path with optional authentication and query parameters.", "scope": "", "scopeKind": ""}, {"name": "apiPost(path, body, auth = false)", "description": "Performs an HTTP POST request to the specified API path with a JSON body, supporting authentication.", "scope": "", "scopeKind": ""}, {"name": "apiPatch(path, body, auth = false)", "description": "Performs an HTTP PATCH request to the specified API path with a JSON body, supporting authentication.", "scope": "", "scopeKind": ""}, {"name": "apiDelete(path, auth = false)", "description": "Performs an HTTP DELETE request to the specified API path, supporting authentication, and handles 204 No Content responses.", "scope": "", "scopeKind": ""}, {"name": "getHeaders(auth = false)", "scope": "", "scopeKind": "", "description": "unavailable"}], "calls": ["fetch", "localStorage.getItem", "localStorage.setItem", "localStorage.removeItem", "Object.entries", "url.searchParams.append", "url.searchParams.set", "res.ok", "res.text", "res.json"], "search-terms": ["api", "fetch", "HTTP", "JavaScript API client", "token management"], "state": 2, "file_id": 13, "knowledge_revision": 31, "git_revision": "", "ctags": [{"_type": "tag", "name": "API_BASE", "path": "/home/kavia/workspace/code-generation/recipe-hub-9586-9605/recipe_frontend/src/services/api.js", "pattern": "/^const API_BASE = process.env.REACT_APP_API_BASE_URL || 'http:\\/\\/localhost:3001';$/", "language": "JavaScript", "kind": "constant"}, {"_type": "tag", "name": "Content-Type", "path": "/home/kavia/workspace/code-generation/recipe-hub-9586-9605/recipe_frontend/src/services/api.js", "pattern": "/^  const headers = { 'Content-Type': 'application\\/json' };$/", "language": "JavaScript", "kind": "property", "scope": "getHeaders.headers", "scopeKind": "class"}, {"_type": "tag", "name": "apiDelete", "path": "/home/kavia/workspace/code-generation/recipe-hub-9586-9605/recipe_frontend/src/services/api.js", "pattern": "/^export async function apiDelete(path, auth = false) {$/", "language": "JavaScript", "kind": "function", "signature": "(path, auth = false)"}, {"_type": "tag", "name": "apiGet", "path": "/home/kavia/workspace/code-generation/recipe-hub-9586-9605/recipe_frontend/src/services/api.js", "pattern": "/^export async function apiGet(path, auth = false, params) {$/", "language": "JavaScript", "kind": "function", "signature": "(path, auth = false, params)"}, {"_type": "tag", "name": "apiPatch", "path": "/home/kavia/workspace/code-generation/recipe-hub-9586-9605/recipe_frontend/src/services/api.js", "pattern": "/^export async function apiPatch(path, body, auth = false) {$/", "language": "JavaScript", "kind": "function", "signature": "(path, body, auth = false)"}, {"_type": "tag", "name": "apiPost", "path": "/home/kavia/workspace/code-generation/recipe-hub-9586-9605/recipe_frontend/src/services/api.js", "pattern": "/^export async function apiPost(path, body, auth = false) {$/", "language": "JavaScript", "kind": "function", "signature": "(path, body, auth = false)"}, {"_type": "tag", "name": "getHeaders", "path": "/home/kavia/workspace/code-generation/recipe-hub-9586-9605/recipe_frontend/src/services/api.js", "pattern": "/^function getHeaders(auth = false) {$/", "language": "JavaScript", "kind": "function", "signature": "(auth = false)"}, {"_type": "tag", "name": "headers", "path": "/home/kavia/workspace/code-generation/recipe-hub-9586-9605/recipe_frontend/src/services/api.js", "pattern": "/^  const headers = { 'Content-Type': 'application\\/json' };$/", "language": "JavaScript", "kind": "class", "scope": "getHeaders", "scopeKind": "class"}, {"_type": "tag", "name": "setAuthToken", "path": "/home/kavia/workspace/code-generation/recipe-hub-9586-9605/recipe_frontend/src/services/api.js", "pattern": "/^export function setAuthToken(token) {$/", "language": "JavaScript", "kind": "function", "signature": "(token)"}], "hash": "e0a3caea657bead4d407056061aefb4e", "format-version": 4, "code-base-name": "recipe_frontend", "filename": "recipe_frontend/src/services/api.js", "fields": [{"name": "const headers = { 'Content-Type': 'application\\/json' };", "scope": "getHeaders.headers", "scopeKind": "class", "description": "unavailable"}], "revision_history": [{"31": ""}]}